trequests/__init__.py
trequests/trequests_version.txt
trequests_xsren-1.0.3.dist-info/DESCRIPTION.rst
trequests_xsren-1.0.3.dist-info/METADATA
trequests_xsren-1.0.3.dist-info/RECORD
trequests_xsren-1.0.3.dist-info/WHEEL
trequests_xsren-1.0.3.dist-info/metadata.json
trequests_xsren-1.0.3.dist-info/top_level.txt
