Metadata-Version: 2.0
Name: trequests-xsren
Version: 1.0.3
Summary: A Tornado async HTTP/HTTPS client adaptor for python-requests. Forked from https://github.com/1stvamp/trequests .
Home-page: https://github.com/xsren/trequests
Author: xsren
Author-email: bestrenxs@gmail.com
License: BSD
Platform: UNKNOWN
Requires-Dist: greenlet (>=0.4)
Requires-Dist: pycurl (>=7.18.2)
Requires-Dist: requests (>=1.0.0)
Requires-Dist: tornado (>=2.0.0)
Requires-Dist: tornalet (>=1.0.2)
